src/.env
src/__init__.py
src/lib.py
src/server.py
mcp_auth0_audit_ips-0.1.1.dist-info/METADATA
mcp_auth0_audit_ips-0.1.1.dist-info/WHEEL
mcp_auth0_audit_ips-0.1.1.dist-info/entry_points.txt
mcp_auth0_audit_ips-0.1.1.dist-info/RECORD
